<ForceField>
    <LennardJonesForce lj14scale="0.50000">
        <Atom epsilon="2.104806376853607" sigma="0.40082" type="Al"/>
        <Atom epsilon="0.39861143730982884" sigma="0.34309" type="C"/>
        <Atom epsilon="0.1625141143352284" sigma="0.25711" type="H"/>
        <Atom epsilon="0.27669545366692994" sigma="0.31181" type="O"/>
        <Atom epsilon="0.6443589176300152" sigma="0.305" type="O_co2"/>
        <Atom epsilon="0.18280448977372507" sigma="0.28" type="C_co2"/>
    </LennardJonesForce>
</ForceField>
