<ForceField>
    <LennardJonesForce lj14scale="0.50000">
        <Atom epsilon="2.098720756617379" sigma="0.40082" type="Al"/>
        <Atom epsilon="0.3959739332972258" sigma="0.34309" type="C"/>
        <Atom epsilon="0.16266886639673644" sigma="0.25711" type="H"/>
        <Atom epsilon="0.28045875736524417" sigma="0.31181" type="O"/>
        <Atom epsilon="0.6407053062983866" sigma="0.305" type="O_co2"/>
        <Atom epsilon="0.18898170173626833" sigma="0.28" type="C_co2"/>
    </LennardJonesForce>
</ForceField>
